slencode-0.1.1.dist-info/METADATA
slencode-0.1.1.dist-info/WHEEL
slencode/__init__.py
slencode/slencode.cp312-win_amd64.pyd
slencode-0.1.1.dist-info/RECORD
